LICENSE.txt
README.txt
setup.py
disthelper/__init__.py
disthelper.egg-info/PKG-INFO
disthelper.egg-info/SOURCES.txt
disthelper.egg-info/dependency_links.txt
disthelper.egg-info/entry_points.txt
disthelper.egg-info/requires.txt
disthelper.egg-info/top_level.txt
disthelper/cmd/__init__.py
disthelper/templates/__init__.py
disthelper/templates/distcmd_package/+package+/__init__.py
disthelper/templates/distcmd_package/+package+/+distcmds_mod+/+command+.py_tmpl
disthelper/templates/distcmd_package/+package+/+distcmds_mod+/__init__.py
disthelper/tests/__init__.py
disthelper/tests/test_cmd.py
disthelper/tests/test_distcmd.py
old-way/setup.cfg
old-way/setup.py
old-way/foo/__init__.py
old-way/foo/distutils_commands/__init__.py
old-way/foo/distutils_commands/build_docs.py
