Metadata-Version: 1.0
Name: disthelper
Version: 0.9.2
Summary: helps you manage a Python distribution
Home-page: http://code.google.com/p/disthelper/
Author: Kumar McMillan
Author-email: kumar.mcmillan@gmail.com
License: New BSD License
Platform: UNKNOWN
